playervectors/__init__.py
playervectors/extract_data.py
playervectors/playervectors.py
playervectors-0.1.0.dist-info/LICENSE
playervectors-0.1.0.dist-info/METADATA
playervectors-0.1.0.dist-info/WHEEL
playervectors-0.1.0.dist-info/top_level.txt
playervectors-0.1.0.dist-info/RECORD
